{"TESTING": false, "NTRIALS": 10, "NCUES": 20, "GRID_TYPE": ".\\data\\training-intermediate-data\\training-grids\\2019-06-12_10-01_grid_NonLinearInteractionGrid_12-12_64-64.pkl", "PROCESSOR_TYPE": "net", "NO_NUMPAD": false, "ENCODER": ".\\data\\training-intermediate-data\\training-encoders\\2019-06-12_10-01_encoder_NonLinearInteractionGrid_12-12_64-64.h5", "WITH_SCANNING": false, "XSIZE": 144, "YSIZE": 144, "SCALE": 12, "EXSIZE": 12, "EYSIZE": 12, "INPUT_XSIZE": 64, "INPUT_YSIZE": 64, "IMAGE_TEMPLATE": "./data/digit-images-aliased/{}.png", "IMAGE_SIZE": [72, 72, 4], "IMAGE_SCALE": 0.16666666666666666, "DATETIME_FORMAT": "%Y-%m-%d_%H-%M-%S", "DIGIT_SOUND_TEMPLATE": "./data/digit-voice/{}-alt.wav", "CONFIG_FILE_TEMPLATE": "./data/psychophysics-sessions/participants/{}_{}_config.json", "SESSION_FILE_TEMPLATE": "./data/psychophysics-sessions/participants/{}_{}_session.csv", "MOUSE_FILE_TEMPLATE": "./data/psychophysics-sessions/participants/{}_{}_mouse.csv", "CORRECT_NOTE": "G", "INCORRECT_NOTE": "Csh", "NOTE_DURATION": 0.1, "NOTE_VOLUME": 0.5, "SESSION_VARS": ["trial", "cue", "digit", "keypress", "cuetime", "trialtime", "sessiontime"], "MOUSE_VARS": ["trial", "cue", "digit", "xmouse", "ymouse", "cuetime", "trialtime", "sessiontime"], "SESSION_HEADER": "trial,cue,digit,keypress,cuetime,trialtime,sessiontime\n", "SESSION_ROW_TEMPLATE": "{trial},{cue},{digit},{keypress},{cuetime},{trialtime},{sessiontime}\n", "MOUSE_HEADER": "trial,cue,digit,xmouse,ymouse,cuetime,trialtime,sessiontime\n", "MOUSE_ROW_TEMPLATE": "{trial},{cue},{digit},{xmouse},{ymouse},{cuetime},{trialtime},{sessiontime}\n", "MOUSE_RECORD_INTERVAL": 0.2, "PROMPT_TEXT": "{}% complete.\n\nPress any key when ready.", "END_TEXT": "Thank you. \n\nPress any key to exit.", "KEY_LIST": ["num_0", "num_1", "num_2", "num_3", "num_4", "num_5", "num_6", "num_7", "num_8", "num_9"], "EXCLUDED": ["STIMULI", "GRID", "IMAGES", "BLANK_IMAGE", "PROCESSOR"], "details": {"datetime": "2019-06-17_10-19-11", "participant": "JW"}, "configFile": "./data/psychophysics-sessions/participants/JW_2019-06-17_10-19-11_config.json", "sessionFile": "./data/psychophysics-sessions/participants/JW_2019-06-17_10-19-11_session.csv", "mouseFile": "./data/psychophysics-sessions/participants/JW_2019-06-17_10-19-11_mouse.csv"}